mpanalyze/__init__.py
mpanalyze/analyze.py
mpanalyze/generate_cahrts.py
mpanalyze/get_params_dict.py
mpanalyze/utils.py
mpanalyze-0.3.dist-info/LICENSE
mpanalyze-0.3.dist-info/METADATA
mpanalyze-0.3.dist-info/WHEEL
mpanalyze-0.3.dist-info/entry_points.txt
mpanalyze-0.3.dist-info/top_level.txt
mpanalyze-0.3.dist-info/RECORD
