Metadata-Version: 2.1
Name: mpanalyze
Version: 0.3
Summary: A package for analyzing model parameters
Home-page: https://github.com/JJLi0427/Model_Params_Analyze
Author: Jiajun Li
Author-email: 2366876022@qq.com
Classifier: License :: OSI Approved :: MIT License
Classifier: Programming Language :: Python
Classifier: Programming Language :: Python :: 3
Classifier: Programming Language :: Python :: 3.8
License-File: LICENSE
Requires-Dist: pyecharts
